file_server/__init__.py
file_server/lib/__init__.py
file_server/lib/server_handler.py
file_server/main.py
file_server_ez-0.1.0.dist-info/METADATA
file_server_ez-0.1.0.dist-info/WHEEL
file_server_ez-0.1.0.dist-info/entry_points.txt
file_server_ez-0.1.0.dist-info/RECORD
